AUTHORS.rst
CONTRIBUTING.rst
HISTORY.rst
LICENSE
MANIFEST.in
README.md
setup.cfg
setup.py
docs/Makefile
docs/authors.rst
docs/conf.py
docs/contributing.rst
docs/history.rst
docs/index.rst
docs/installation.rst
docs/make.bat
docs/readme.rst
docs/usage.rst
docs/_build/html/_static/file.png
docs/_build/html/_static/minus.png
docs/_build/html/_static/plus.png
docs/_build/html/_static/images/logo_colab.png
gui/breeze.qrc
gui/breeze_resources.py
gui/dark.qss
gui/dark/branch_closed-on.svg
gui/dark/branch_closed.svg
gui/dark/branch_open-on.svg
gui/dark/branch_open.svg
gui/dark/checkbox_checked.svg
gui/dark/checkbox_checked_disabled.svg
gui/dark/checkbox_indeterminate.svg
gui/dark/checkbox_indeterminate_disabled.svg
gui/dark/checkbox_unchecked.svg
gui/dark/checkbox_unchecked_disabled.svg
gui/dark/close-hover.svg
gui/dark/close-pressed.svg
gui/dark/close.svg
gui/dark/down_arrow-hover.svg
gui/dark/down_arrow.svg
gui/dark/down_arrow_disabled.svg
gui/dark/hmovetoolbar.svg
gui/dark/hsepartoolbar.svg
gui/dark/left_arrow.svg
gui/dark/left_arrow_disabled.svg
gui/dark/radio_checked.svg
gui/dark/radio_checked_disabled.svg
gui/dark/radio_unchecked.svg
gui/dark/radio_unchecked_disabled.svg
gui/dark/right_arrow.svg
gui/dark/right_arrow_disabled.svg
gui/dark/sizegrip.svg
gui/dark/spinup_disabled.svg
gui/dark/stylesheet-branch-end-closed.svg
gui/dark/stylesheet-branch-end-open.svg
gui/dark/stylesheet-branch-end.svg
gui/dark/stylesheet-branch-more.svg
gui/dark/stylesheet-vline.svg
gui/dark/transparent.svg
gui/dark/undock-hover.svg
gui/dark/undock.svg
gui/dark/up_arrow-hover.svg
gui/dark/up_arrow.svg
gui/dark/up_arrow_disabled.svg
gui/dark/vmovetoolbar.svg
gui/dark/vsepartoolbars.svg
gui/ui/main.ui
perry_bot/__init__.py
perry_bot/backend.py
perry_bot/cli_entry.py
perry_bot/gui.py
perry_bot/main.py
perry_bot.egg-info/PKG-INFO
perry_bot.egg-info/SOURCES.txt
perry_bot.egg-info/dependency_links.txt
perry_bot.egg-info/entry_points.txt
perry_bot.egg-info/not-zip-safe
perry_bot.egg-info/requires.txt
perry_bot.egg-info/top_level.txt
tests/conftest.py
tests/test_perry_bot.py