Metadata-Version: 2.1
Name: perry-bot
Version: 0.1.0
Summary: A self care bot.
Home-page: https://github.com/shunnkou/perry_bot
Author: Jace Huang
Author-email: jacehuang8@protonmail.ch
License: BSD license
Keywords: perry_bot
Platform: UNKNOWN
Classifier: Development Status :: 2 - Pre-Alpha
Classifier: Intended Audience :: End Users/Desktop
Classifier: License :: OSI Approved :: BSD License
Classifier: Natural Language :: English
Classifier: Programming Language :: Python :: 3
Classifier: Programming Language :: Python :: 3.7
Classifier: Programming Language :: Python :: 3.8
Classifier: Programming Language :: Python :: 3.9
Requires-Python: >=3.7
